CHANGELOG.md
LICENSE
MANIFEST.in
Makefile
README.md
setup.cfg
setup.py
tox.ini
tests/test_drf_confirmation_pipeline.py
tests/test_drf_user_config_manipulation.py
tests/test_drf_vocabulary.py
wc_django_2factor.egg-info/PKG-INFO
wc_django_2factor.egg-info/SOURCES.txt
wc_django_2factor.egg-info/dependency_links.txt
wc_django_2factor.egg-info/requires.txt
wc_django_2factor.egg-info/top_level.txt
wcd_2factor/__init__.py
wcd_2factor/admin.py
wcd_2factor/apps.py
wcd_2factor/conf.py
wcd_2factor/const.py
wcd_2factor/exceptions.py
wcd_2factor/registries.py
wcd_2factor/translation.py
wcd_2factor/builtins/__init__.py
wcd_2factor/builtins/dummy.py
wcd_2factor/confirmer/__init__.py
wcd_2factor/confirmer/backends.py
wcd_2factor/confirmer/confirmer.py
wcd_2factor/contrib/__init__.py
wcd_2factor/contrib/drf/__init__.py
wcd_2factor/contrib/drf/fields.py
wcd_2factor/contrib/drf/helpers.py
wcd_2factor/contrib/drf/serializers.py
wcd_2factor/contrib/drf/views.py
wcd_2factor/contrib/wcd_jwt/__init__.py
wcd_2factor/contrib/wcd_jwt/serializers.py
wcd_2factor/locale/af/LC_MESSAGES/django.mo
wcd_2factor/locale/af/LC_MESSAGES/django.po
wcd_2factor/locale/ar/LC_MESSAGES/django.mo
wcd_2factor/locale/ar/LC_MESSAGES/django.po
wcd_2factor/locale/ast/LC_MESSAGES/django.mo
wcd_2factor/locale/ast/LC_MESSAGES/django.po
wcd_2factor/locale/az/LC_MESSAGES/django.mo
wcd_2factor/locale/az/LC_MESSAGES/django.po
wcd_2factor/locale/be/LC_MESSAGES/django.mo
wcd_2factor/locale/be/LC_MESSAGES/django.po
wcd_2factor/locale/bg/LC_MESSAGES/django.mo
wcd_2factor/locale/bg/LC_MESSAGES/django.po
wcd_2factor/locale/bn/LC_MESSAGES/django.mo
wcd_2factor/locale/bn/LC_MESSAGES/django.po
wcd_2factor/locale/br/LC_MESSAGES/django.mo
wcd_2factor/locale/br/LC_MESSAGES/django.po
wcd_2factor/locale/bs/LC_MESSAGES/django.mo
wcd_2factor/locale/bs/LC_MESSAGES/django.po
wcd_2factor/locale/ca/LC_MESSAGES/django.mo
wcd_2factor/locale/ca/LC_MESSAGES/django.po
wcd_2factor/locale/cs/LC_MESSAGES/django.mo
wcd_2factor/locale/cs/LC_MESSAGES/django.po
wcd_2factor/locale/cy/LC_MESSAGES/django.mo
wcd_2factor/locale/cy/LC_MESSAGES/django.po
wcd_2factor/locale/da/LC_MESSAGES/django.mo
wcd_2factor/locale/da/LC_MESSAGES/django.po
