Metadata-Version: 2.1
Name: wc-django-2factor
Version: 0.2.0
Summary: Package to create general API for 2factor checkers.
Author: WebCase
Author-email: info@webcase.studio
License: MIT License
Classifier: Development Status :: 2 - Pre-Alpha
Classifier: Programming Language :: Python :: 3
Classifier: Intended Audience :: Developers
Classifier: Topic :: Utilities
Classifier: License :: OSI Approved :: MIT License
Classifier: Operating System :: OS Independent
Requires-Python: >=3.6
License-File: LICENSE
Requires-Dist: pydantic
Requires-Dist: django-jsonform<=3.0.0,>=2.1.0
Requires-Dist: px-settings<0.2.0,>=0.1.2
Requires-Dist: wc-django-notifications<0.4.0,>=0.1.3
Requires-Dist: wc-django-settings<0.2.0,>=0.1.0
Requires-Dist: preusx-django-admin-extensions<0.2.0,>=0.1.6
Provides-Extra: dev
Requires-Dist: pytest<9.0,>=8.0; extra == "dev"
Requires-Dist: pytest-mock<4.0.0,>=3.10.0; extra == "dev"
Requires-Dist: pytest-watch<5.0,>=4.2; extra == "dev"
Requires-Dist: pytest-django<5.0,>=4.3; extra == "dev"
Requires-Dist: django-environ==0.11.2; extra == "dev"
Requires-Dist: django-stubs; extra == "dev"
Requires-Dist: django; extra == "dev"
Requires-Dist: twine; extra == "dev"
